ea_core_base.py
ea_core_base-0.4.dist-info/METADATA
ea_core_base-0.4.dist-info/WHEEL
ea_core_base-0.4.dist-info/top_level.txt
ea_core_base-0.4.dist-info/RECORD
