Metadata-Version: 2.1
Name: ea-core-base
Version: 0.4
Summary: Energy Analysis Core Base
Home-page: UNKNOWN
Author: Kambiz Ezzati
Author-email: kezzati@armstrongfluidtechnology.com
License: UNKNOWN
Platform: UNKNOWN
Requires-Dist: pydantic
